LICENSE
MANIFEST.in
NEWS
README.rst
pglookout.json
pglookout.spec
pglookout.unit
setup.py
version.py
debian/.gitignore
debian/changelog.in
debian/compat
debian/control
debian/copyright
debian/docs
debian/postinst
debian/rules
examples/failover.sh
examples/init_slave.sh
examples/pglookout_supervisord.conf
pglookout/__init__.py
pglookout/__main__.py
pglookout/cluster_monitor.py
pglookout/common.py
pglookout/current_master.py
pglookout/logutil.py
pglookout/pglookout.py
pglookout/pgutil.py
pglookout/statsd.py
pglookout/version.py
pglookout/webserver.py
pglookout.egg-info/PKG-INFO
pglookout.egg-info/SOURCES.txt
pglookout.egg-info/dependency_links.txt
pglookout.egg-info/entry_points.txt
pglookout.egg-info/not-zip-safe
pglookout.egg-info/requires.txt
pglookout.egg-info/top_level.txt
test/__init__.py
test/conftest.py
test/test_cluster_monitor.py
test/test_common.py
test/test_lookout.py
test/test_pgutil.py
test/test_webserver.py